bootlets/__init__.py
bootlets/base.py
bootlets/decorators.py
bootlets/functions.py
bootlets/templates.py
bootlets/utils.py
bootlets-0.0.2.dist-info/METADATA
bootlets-0.0.2.dist-info/WHEEL
bootlets-0.0.2.dist-info/top_level.txt
bootlets-0.0.2.dist-info/RECORD
