Metadata-Version: 2.1
Name: bootlets
Version: 0.0.2
Summary: Build HTML in Python
Home-page: https://github.com/NixonInnes/bootlets
Author: NixonInnes
Author-email: nixoninnes@echonet.io
License: MIT
Platform: UNKNOWN
